mistral_vectordb/__init__.py
mistral_vectordb/collections.py
mistral_vectordb/config.py
mistral_vectordb/document_processor.py
mistral_vectordb/init.py
mistral_vectordb/setup_tool.py
mistral_vectordb/store.py
mistral_vectordb/types.py
mistral_vectordb/security/__init__.py
mistral_vectordb/security/audit.py
mistral_vectordb/security/crypto.py
mistral_vectordb/security/manager.py
mistral_vectordb/security/rate_limiter.py
mistral_vectordb/security/schemas.py
mistral_vectordb/server/__init__.py
mistral_vectordb/server/api.py
mistral_vectordb-1.0.0.dist-info/LICENSE
mistral_vectordb-1.0.0.dist-info/METADATA
mistral_vectordb-1.0.0.dist-info/WHEEL
mistral_vectordb-1.0.0.dist-info/entry_points.txt
mistral_vectordb-1.0.0.dist-info/top_level.txt
mistral_vectordb-1.0.0.dist-info/RECORD
