Metadata-Version: 2.1
Name: mistral-vectordb
Version: 1.0.0
Summary: High-performance vector database with secure storage, advanced document processing, and RAG features
Home-page: https://github.com/veerakrish/mistral-vectordb
Author: viswanath veera krishna maddinala
Author-email: veerukhannan@gmail.com
Classifier: Development Status :: 5 - Production/Stable
Classifier: Intended Audience :: Developers
Classifier: License :: OSI Approved :: MIT License
Classifier: Programming Language :: Python :: 3
Classifier: Programming Language :: Python :: 3.8
Classifier: Programming Language :: Python :: 3.9
Classifier: Programming Language :: Python :: 3.10
Classifier: Topic :: Software Development :: Libraries :: Python Modules
Classifier: Topic :: Database
Classifier: Topic :: Security
Requires-Python: >=3.8
License-File: LICENSE
Requires-Dist: numpy>=1.19.0
Requires-Dist: fastapi>=0.68.0
Requires-Dist: uvicorn>=0.15.0
Requires-Dist: python-jose[cryptography]>=3.3.0
Requires-Dist: python-multipart>=0.0.5
Requires-Dist: requests>=2.26.0
Requires-Dist: pydantic>=1.8.0
Requires-Dist: PyYAML>=5.4.1
Requires-Dist: cryptography>=3.4.7
Requires-Dist: python-dateutil>=2.8.2
Requires-Dist: aiohttp>=3.8.0
Requires-Dist: prometheus-client>=0.12.0
Requires-Dist: psutil>=5.8.0
Provides-Extra: dev
Requires-Dist: pytest>=6.2.5; extra == "dev"
Requires-Dist: black>=21.9b0; extra == "dev"
Requires-Dist: isort>=5.9.3; extra == "dev"
Requires-Dist: flake8>=3.9.2; extra == "dev"
Requires-Dist: mypy>=0.910; extra == "dev"
